pgeof/__init__.py
pgeof/pgeof_ext.cp312-win_amd64.pyd
pgeof/pgeof_ext.pyi
pgeof/py.typed
pgeof-0.3.3.dist-info/METADATA
pgeof-0.3.3.dist-info/WHEEL
pgeof-0.3.3.dist-info/licenses/LICENSE
pgeof-0.3.3.dist-info/RECORD
