Metadata-Version: 2.1
Name: pgeof
Version: 0.3.3
Summary: Compute the geometric features associated with each point's neighborhood:
Keywords: point clouds,features,3D,LiDAR
Author-Email: Loic Landrieu <loic.landrieu@enpc.fr>, Damien Robert <damien.robert@uzh.ch>
License: MIT License
Classifier: Development Status :: 3 - Alpha
Classifier: Programming Language :: Python
Classifier: Topic :: Scientific/Engineering
Project-URL: homepage, https://github.com/drprojects/point_geometric_features
Project-URL: repository, https://github.com/drprojects/point_geometric_features
Requires-Python: <3.14,>=3.8
Requires-Dist: numpy>=1.7
